README.txt
bootstrap.py
buildout.cfg
setup.py
docs/HISTORY.txt
src/collective/__init__.py
src/collective.catalogexport.egg-info/PKG-INFO
src/collective.catalogexport.egg-info/SOURCES.txt
src/collective.catalogexport.egg-info/dependency_links.txt
src/collective.catalogexport.egg-info/entry_points.txt
src/collective.catalogexport.egg-info/namespace_packages.txt
src/collective.catalogexport.egg-info/not-zip-safe
src/collective.catalogexport.egg-info/requires.txt
src/collective.catalogexport.egg-info/top_level.txt
src/collective/catalogexport/README.txt
src/collective/catalogexport/__init__.py
src/collective/catalogexport/configure.zcml
src/collective/catalogexport/export.py
src/collective/catalogexport/tests.py
src/collective/catalogexport/tests.zcml