Metadata-Version: 1.0
Name: collective.catalogexport
Version: 0.1
Summary: Use ZCatalogs as export sources
Home-page: http://pypi.python.org/pypi/collective.catalogexport
Author: Ross Patterson
Author-email: me@rpatterson.net
License: GPL
Platform: UNKNOWN
Classifier: Programming Language :: Python
Classifier: Topic :: Software Development :: Libraries :: Python Modules
